marl_aquarium/__init__.py
marl_aquarium/aquarium_v0.py
marl_aquarium/env/__init__.py
marl_aquarium/env/animal.py
marl_aquarium/env/aquarium.py
marl_aquarium/env/predator.py
marl_aquarium/env/prey.py
marl_aquarium/env/utils.py
marl_aquarium/env/vector.py
marl_aquarium/env/view.py
marl_aquarium/env/assets/__init__.py
marl_aquarium/env/assets/predator.png
marl_aquarium/env/assets/prey.png
marl_aquarium-0.1.10.dist-info/LICENSE
marl_aquarium-0.1.10.dist-info/METADATA
marl_aquarium-0.1.10.dist-info/WHEEL
marl_aquarium-0.1.10.dist-info/top_level.txt
marl_aquarium-0.1.10.dist-info/RECORD
