Metadata-Version: 2.1
Name: marl-aquarium
Version: 0.1.10
Summary: Aquarium: A Comprehensive Framework for Exploring Predator-Prey Dynamics through Multi-Agent Reinforcement Learning Algorithms
Home-page: https://github.com/michaelkoelle/marl-aquarium
Author: Yannick Erpelding and Michael Kölle
Author-email: michael.koelle@ifi.lmu.de
License: MIT
Keywords: artificial intelligence,pettingzoo,multi-agent,reinforcement learning,deep learning,predator-prey,gymnasium,gym
Classifier: Programming Language :: Python :: 3
Classifier: License :: OSI Approved :: MIT License
Classifier: Operating System :: OS Independent
Requires-Python: >=3.8
License-File: LICENSE
Requires-Dist: gymnasium ==0.28.1
Requires-Dist: moviepy ==1.0.3
Requires-Dist: numpy ==1.22.4
Requires-Dist: pettingzoo ==1.24.2
Requires-Dist: pygame ==2.1.3
